MANIFEST.in
README.rst
setup.py
tgext/__init__.py
tgext.browserlimit.egg-info/PKG-INFO
tgext.browserlimit.egg-info/SOURCES.txt
tgext.browserlimit.egg-info/dependency_links.txt
tgext.browserlimit.egg-info/entry_points.txt
tgext.browserlimit.egg-info/namespace_packages.txt
tgext.browserlimit.egg-info/not-zip-safe
tgext.browserlimit.egg-info/top_level.txt
tgext/browserlimit/__init__.py
tgext/browserlimit/limits.py
tgext/browserlimit/middleware.py
tgext/browserlimit/useragent_parser.py
tgext/browserlimit/public/__init__.py
tgext/browserlimit/public/chrome.png
tgext/browserlimit/public/firefox.png
tgext/browserlimit/public/ie.png
tgext/browserlimit/public/safari.png
tgext/browserlimit/public/unsupported.html