Metadata-Version: 1.1
Name: tgext.browserlimit
Version: 0.1.2
Summary: High Level Browser Detection Middleware for Turbogears 2, limits access to website only for modern browsers
Home-page: http://bitbucket.org/_amol_/tgext.browserlimit
Author: Alessandro Molina
Author-email: alessandro.molina@axant.it
License: MIT
Keywords: turbogears2.extension
Platform: UNKNOWN
Classifier: Environment :: Web Environment
Classifier: Topic :: Software Development :: Libraries :: Python Modules
Classifier: Framework :: TurboGears
